docshtest.py
docshtest-0.0.3.dist-info/LICENSE
docshtest-0.0.3.dist-info/METADATA
docshtest-0.0.3.dist-info/WHEEL
docshtest-0.0.3.dist-info/entry_points.txt
docshtest-0.0.3.dist-info/top_level.txt
docshtest-0.0.3.dist-info/RECORD
