Metadata-Version: 2.1
Name: docshtest
Version: 0.0.3
Summary: Doctest for shell commands
Home-page: http://github.com/0k/docshtest
Author: Valentin Lab
Author-email: valentin.lab@kalysto.org
License: BSD 3-Clause License
Platform: UNKNOWN
Classifier: Intended Audience :: Developers
Classifier: License :: OSI Approved :: BSD License
Classifier: Topic :: Software Development
Classifier: Topic :: Software Development :: Testing
Classifier: Development Status :: 2 - Pre-Alpha
Classifier: Programming Language :: Unix Shell
Classifier: Programming Language :: Python :: 2.7
Classifier: Programming Language :: Python :: 3
Classifier: Programming Language :: Python :: 3.3
Classifier: Programming Language :: Python :: 3.4
Classifier: Programming Language :: Python :: 3.5
Classifier: Programming Language :: Python :: 3.6
Classifier: Programming Language :: Python :: 3.7
Provides-Extra: test
